{"cameraMode":{"drawMode":0,"name":"Shaded","section":"Shading Mode"},"sceneLighting":true,"audioPlay":false,"sceneViewState":{"m_AlwaysRefresh":false,"showFog":true,"showSkybox":true,"showFlares":true,"showImageEffects":true,"showParticleSystems":true,"showVisualEffectGraphs":true,"m_FxEnabled":true},"in2DMode":false,"pivot":{"x":29.869731903076173,"y":72.52476501464844,"z":24.070032119750978},"rotation":{"x":-0.1490677148103714,"y":0.8493518829345703,"z":-0.3287575840950012,"w":-0.3851185441017151},"size":10.0,"orthographic":false}